lXtractor/__about__.py
lXtractor/__init__.py
lXtractor/py.typed
lXtractor/chain/__init__.py
lXtractor/chain/base.py
lXtractor/chain/chain.py
lXtractor/chain/initializer.py
lXtractor/chain/io.py
lXtractor/chain/list.py
lXtractor/chain/sequence.py
lXtractor/chain/structure.py
lXtractor/chain/tree.py
lXtractor/collection/__init__.py
lXtractor/collection/callbacks.py
lXtractor/collection/collection.py
lXtractor/collection/constructor.py
lXtractor/collection/support.py
lXtractor/core/__init__.py
lXtractor/core/alignment.py
lXtractor/core/base.py
lXtractor/core/config.py
lXtractor/core/exceptions.py
lXtractor/core/interface.py
lXtractor/core/ligand.py
lXtractor/core/pocket.py
lXtractor/core/segment.py
lXtractor/core/structure.py
lXtractor/ext/__init__.py
lXtractor/ext/alphafold.py
lXtractor/ext/base.py
lXtractor/ext/ccd.py
lXtractor/ext/dssp.py
lXtractor/ext/hmm.py
lXtractor/ext/panther.py
lXtractor/ext/pdb_.py
lXtractor/ext/sifts.py
lXtractor/ext/uniprot.py
lXtractor/protocols/__init__.py
lXtractor/protocols/superpose.py
lXtractor/resources/PFP.csv
lXtractor/resources/__init__.py
lXtractor/resources/all21.msgpack
lXtractor/resources/collection_config.json
lXtractor/resources/collection_user_config.json
lXtractor/resources/default_config.json
lXtractor/resources/user_config.json
lXtractor/util/__init__.py
lXtractor/util/io.py
lXtractor/util/misc.py
lXtractor/util/seq.py
lXtractor/util/structure.py
lXtractor/util/typing.py
lXtractor/variables/__init__.py
lXtractor/variables/base.py
lXtractor/variables/calculator.py
lXtractor/variables/ligand.py
lXtractor/variables/manager.py
lXtractor/variables/parser.py
lXtractor/variables/sequential.py
lXtractor/variables/structural.py
lXtractor/variables/util.py
lxtractor-0.1.7.dist-info/METADATA
lxtractor-0.1.7.dist-info/WHEEL
lxtractor-0.1.7.dist-info/licenses/LICENSE
lxtractor-0.1.7.dist-info/RECORD
