Metadata-Version: 2.1
Name: lXtractor
Version: 0.1.7
Summary: Feature extraction library for sequences and structures
Project-URL: Source code, https://github.com/edikedik/lXtractor
Project-URL: Bug Tracker, https://github.com//edikedik/lXtractor/issues
Author-email: Ivan Reveguk <ivan.reveguk@gmail.com>
Maintainer-email: Ivan Reveguk <ivan.reveguk@gmail.com>
License-File: LICENSE
Keywords: bioinformatics,data_mining,feature_extracton,structural_biology
Classifier: Development Status :: 3 - Alpha
Classifier: Operating System :: MacOS
Classifier: Operating System :: POSIX :: Linux
Classifier: Programming Language :: Python :: 3 :: Only
Classifier: Programming Language :: Python :: 3.10
Classifier: Programming Language :: Python :: 3.11
Classifier: Programming Language :: Python :: 3.12
Classifier: Topic :: Documentation :: Sphinx
Classifier: Topic :: Scientific/Engineering :: Bio-Informatics
Requires-Python: >=3.10
Requires-Dist: biotite<1.0,>=0.41
Requires-Dist: joblib>=1.2.0
Requires-Dist: loguru>=0.7.2
Requires-Dist: more-itertools>=10.1
Requires-Dist: msgpack>=1.0.5
Requires-Dist: networkx>=2.8.6
Requires-Dist: numpy>=1.23
Requires-Dist: pandas>=1.5
Requires-Dist: pyhmmer>=0.7.1
Requires-Dist: requests>=2.28.1
Requires-Dist: rustworkx>=0.13.2
Requires-Dist: scipy>=1.11.3
Requires-Dist: toolz>=0.12
Requires-Dist: tqdm>=4.64
